quickbe/__init__.py
quickbe/oauth.py
quickbe/utils.py
quickbe-4.3.0.dist-info/METADATA
quickbe-4.3.0.dist-info/WHEEL
quickbe-4.3.0.dist-info/top_level.txt
quickbe-4.3.0.dist-info/RECORD
