Metadata-Version: 2.1
Name: quickbe
Version: 4.3.0
Summary: Quick and simple back-end infrastructure
Home-page: https://github.com/eldad1221/quickbe
Author: Eldad Bishari
Author-email: eldad@1221tlv.org
Classifier: Programming Language :: Python :: 3
Classifier: License :: OSI Approved :: MIT License
Classifier: Operating System :: OS Independent
Requires-Python: >=3.7
Requires-Dist: flask (==2.0.1)
Requires-Dist: cerberus (==1.3.4)
Requires-Dist: schedule (==1.1.0)
Requires-Dist: psutil (==5.9.4)
